tk_normalizer/__init__.py
tk_normalizer/normalizer.py
tk_normalizer-1.1.0.dist-info/licenses/LICENSE
tk_normalizer-1.1.0.dist-info/METADATA
tk_normalizer-1.1.0.dist-info/WHEEL
tk_normalizer-1.1.0.dist-info/top_level.txt
tk_normalizer-1.1.0.dist-info/RECORD
