Metadata-Version: 2.4
Name: tk-normalizer
Version: 1.1.0
Summary: URL normalization library for consistent URL representation
Author-email: Terakeet <engineering@terakeet.com>
Maintainer-email: Terakeet <engineering@terakeet.com>
License: MIT
Project-URL: Homepage, https://github.com/terakeet/tk-normalizer
Project-URL: Repository, https://github.com/terakeet/tk-normalizer.git
Project-URL: Issues, https://github.com/terakeet/tk-normalizer/issues
Project-URL: Documentation, https://github.com/terakeet/tk-normalizer/blob/main/docs/ARCHITECTURE.md
Keywords: url,normalization,canonicalization,web,utilities
Classifier: Development Status :: 4 - Beta
Classifier: Intended Audience :: Developers
Classifier: License :: OSI Approved :: MIT License
Classifier: Programming Language :: Python :: 3
Classifier: Programming Language :: Python :: 3.11
Classifier: Programming Language :: Python :: 3.12
Classifier: Programming Language :: Python :: 3.13
Classifier: Topic :: Internet :: WWW/HTTP
Classifier: Topic :: Software Development :: Libraries :: Python Modules
Classifier: Topic :: Text Processing :: Filters
Classifier: Operating System :: OS Independent
Requires-Python: >=3.11
License-File: LICENSE
Provides-Extra: dev
Requires-Dist: pytest>=7.0.0; extra == "dev"
Requires-Dist: pytest-mock>=3.0.0; extra == "dev"
Requires-Dist: pytest-cov>=4.0.0; extra == "dev"
Requires-Dist: ruff>=0.1.0; extra == "dev"
Requires-Dist: pre-commit>=3.0.0; extra == "dev"
Requires-Dist: build>=0.10.0; extra == "dev"
Requires-Dist: twine>=4.0.0; extra == "dev"
Dynamic: license-file
